restruct/__init__.py
restruct/restruct.py
pyrestruct-0.1.0.dist-info/METADATA
pyrestruct-0.1.0.dist-info/WHEEL
pyrestruct-0.1.0.dist-info/licenses/LICENCE
pyrestruct-0.1.0.dist-info/RECORD
